pydoftk/__about__.py
pydoftk/__init__.py
pydoftk-0.2.0.dist-info/METADATA
pydoftk-0.2.0.dist-info/WHEEL
pydoftk-0.2.0.dist-info/licenses/LICENSE.txt
pydoftk-0.2.0.dist-info/RECORD
