Metadata-Version: 2.1
Name: pydoftk
Version: 0.2.0
Summary: Python Digital Ocean Function Tool Kit
Project-URL: Documentation, https://github.com/rykroon/pydoftk#readme
Project-URL: Issues, https://github.com/rykroon/pydoftk/issues
Project-URL: Source, https://github.com/rykroon/pydoftk
Author-email: Ryan Kroon <rykroon.tech@gmail.com>
License-Expression: MIT
License-File: LICENSE.txt
Classifier: Development Status :: 4 - Beta
Classifier: Programming Language :: Python
Classifier: Programming Language :: Python :: 3.9
Classifier: Programming Language :: Python :: 3.10
Classifier: Programming Language :: Python :: 3.11
Classifier: Programming Language :: Python :: Implementation :: CPython
Requires-Python: >=3.9
Requires-Dist: multidict==6.*
